turbos3_py-0.3.2.dist-info/METADATA
turbos3_py-0.3.2.dist-info/WHEEL
turbos3_py/__init__.py
turbos3_py/turbos3_py.cpython-38-darwin.so
turbos3_py-0.3.2.dist-info/RECORD
