Metadata-Version: 2.1
Name: turbos3_py
Version: 0.3.2
Classifier: Programming Language :: Python :: 3
Classifier: License :: OSI Approved :: MIT License
Classifier: Operating System :: OS Independent
Summary: Turbocharged S3 downloads and uplaods for Python
Author: benjamin ellis <benjaminjellis@protonmail.com>
Author-email: Benjamin Ellis <benjaminjellis@protonmail.com>
License: MIT License
Requires-Python: >=3.7
Project-URL: Bug Tracker, https://github.com/benjaminjellis/turbo/issues
Project-URL: Homepage, https://github.com/benjaminjellis/turbo
